lollipop_jsonschema/__init__.py
lollipop_jsonschema/compat.py
lollipop_jsonschema/jsonschema.py
lollipop_jsonschema-0.9.0.dist-info/licenses/LICENSE
lollipop_jsonschema-0.9.0.dist-info/METADATA
lollipop_jsonschema-0.9.0.dist-info/WHEEL
lollipop_jsonschema-0.9.0.dist-info/top_level.txt
lollipop_jsonschema-0.9.0.dist-info/RECORD
